odoo/addons/mail_gateway_telegram/README.rst
odoo/addons/mail_gateway_telegram/__init__.py
odoo/addons/mail_gateway_telegram/__manifest__.py
odoo/addons/mail_gateway_telegram/i18n/es.po
odoo/addons/mail_gateway_telegram/i18n/es_VE.po
odoo/addons/mail_gateway_telegram/i18n/it.po
odoo/addons/mail_gateway_telegram/i18n/mail_gateway_telegram.pot
odoo/addons/mail_gateway_telegram/models/__init__.py
odoo/addons/mail_gateway_telegram/models/mail_gateway.py
odoo/addons/mail_gateway_telegram/models/mail_gateway_channel.py
odoo/addons/mail_gateway_telegram/models/mail_gateway_telegram.py
odoo/addons/mail_gateway_telegram/readme/CONFIGURE.md
odoo/addons/mail_gateway_telegram/readme/CONTRIBUTORS.md
odoo/addons/mail_gateway_telegram/readme/CREDITS.md
odoo/addons/mail_gateway_telegram/readme/DESCRIPTION.md
odoo/addons/mail_gateway_telegram/readme/USAGE.md
odoo/addons/mail_gateway_telegram/static/description/icon.png
odoo/addons/mail_gateway_telegram/static/description/icon.svg
odoo/addons/mail_gateway_telegram/static/description/index.html
odoo/addons/mail_gateway_telegram/static/src/components/message/message.xml
odoo/addons/mail_gateway_telegram/static/src/models/message.esm.js
odoo/addons/mail_gateway_telegram/static/src/models/message_view.esm.js
odoo/addons/mail_gateway_telegram/static/src/models/notification.esm.js
odoo/addons/mail_gateway_telegram/tests/__init__.py
odoo/addons/mail_gateway_telegram/tests/sticker.tgs
odoo/addons/mail_gateway_telegram/tests/test_mail_gateway_telegram.py
odoo/addons/mail_gateway_telegram/views/mail_gateway.xml
odoo_addon_mail_gateway_telegram-18.0.1.0.0.2.dist-info/METADATA
odoo_addon_mail_gateway_telegram-18.0.1.0.0.2.dist-info/WHEEL
odoo_addon_mail_gateway_telegram-18.0.1.0.0.2.dist-info/top_level.txt
odoo_addon_mail_gateway_telegram-18.0.1.0.0.2.dist-info/RECORD
