Metadata-Version: 2.1
Name: odoo-addon-mail_gateway_telegram
Version: 18.0.1.0.0.2
Requires-Python: >=3.10
Requires-Dist: cairosvg
Requires-Dist: lottie
Requires-Dist: odoo-addon-mail_gateway==18.0.*
Requires-Dist: odoo==18.0.*
Requires-Dist: python-telegram-bot
Summary: Set a gateway for telegram
Home-page: https://github.com/OCA/social
License: AGPL-3
Author: Creu Blanca,Dixmit,Odoo Community Association (OCA)
Author-email: support@odoo-community.org
Classifier: Programming Language :: Python
Classifier: Framework :: Odoo
Classifier: Framework :: Odoo :: 18.0
Classifier: License :: OSI Approved :: GNU Affero General Public License v3
